profile_tool/__init__.py
profile_tool/__main__.py
profile_tool/auth.py
profile_tool/tool.py
profile_tool/version.py
profile_tool/centrify/__init__.py
profile_tool/centrify/adv_authrequest.py
profile_tool/centrify/authrequest.py
profile_tool/centrify/authresponse.py
profile_tool/centrify/awsinputs.py
profile_tool/centrify/cenapp.py
profile_tool/centrify/cenauth.py
profile_tool/centrify/cenauthsession.py
profile_tool/centrify/cenrest.py
profile_tool/centrify/htmlparser.py
profile_tool/centrify/htmlresponse.py
profile_tool/centrify/uprest.py
profile_tool/centrify/user.py
profile_tool/centrify/util.py
profile_tool/centrify/kbread/__init__.py
profile_tool/centrify/kbread/kbinput.py
profile_tool/config/__init__.py
profile_tool/config/apps.py
profile_tool/config/environment.py
profile_tool/config/proxy.py
profile_tool/config/readconfig.py
profile_tool-2.0.8.data/data/profile_tool/eotss.my.crt
profile_tool-2.0.8.dist-info/METADATA
profile_tool-2.0.8.dist-info/WHEEL
profile_tool-2.0.8.dist-info/entry_points.txt
profile_tool-2.0.8.dist-info/top_level.txt
profile_tool-2.0.8.dist-info/RECORD
